py_github_gui/__init__.py
py_github_gui/__main__.py
py_github_gui/placeholder.png
py_github_gui_rackodo-1.1.1.dist-info/LICENSE.md
py_github_gui_rackodo-1.1.1.dist-info/METADATA
py_github_gui_rackodo-1.1.1.dist-info/WHEEL
py_github_gui_rackodo-1.1.1.dist-info/top_level.txt
py_github_gui_rackodo-1.1.1.dist-info/RECORD
