Metadata-Version: 2.1
Name: py-github-gui-rackodo
Version: 1.1.1
Summary: Python GUI for Github using the Github API.
Home-page: https://github.com/rackodo/py-github-gui
Author: Bash Elliott
Author-email: rackodo.business@gmail.com
Project-URL: Bug Tracker, https://github.com/rackodo/py-github-gui/issues
Classifier: Programming Language :: Python :: 3
Classifier: License :: OSI Approved :: MIT License
Classifier: Operating System :: OS Independent
Requires-Python: >=3.7
License-File: LICENSE.md
Requires-Dist: Pillow (==9.5.0)
Requires-Dist: PyGithub (==1.58.1)
Requires-Dist: requests (==2.28.2)
Requires-Dist: url-normalize (==1.4.3)
